py_trees_meet_groot/__init__.py
py_trees_meet_groot/groot_xml.py
py_trees_meet_groot-0.2.dist-info/METADATA
py_trees_meet_groot-0.2.dist-info/WHEEL
py_trees_meet_groot-0.2.dist-info/licenses/LICENSE
py_trees_meet_groot-0.2.dist-info/RECORD
