Metadata-Version: 2.1
Name: py_trees_meet_groot
Version: 0.2
Summary: Library to load XML behavior trees done using Groot GUI (https://github.com/BehaviorTree/Groot) into the py_trees library (https://github.com/splintered-reality/py_trees)
Project-URL: Homepage, https://github.com/narcispr/py_trees_meet_groot
Project-URL: Bug Tracker, https://github.com/pypa/py_trees_meet_groot/issues
Author-email: Narcis Palomeras <narcispr@gmail.com>
License-File: LICENSE
Classifier: License :: OSI Approved :: MIT License
Classifier: Operating System :: OS Independent
Classifier: Programming Language :: Python :: 3
Requires-Python: >=3.7
